bruhcolor/__init__.py
bruhcolor/bruhcolor.py
bruhcolor-0.0.56.dist-info/COPYING.txt
bruhcolor-0.0.56.dist-info/METADATA
bruhcolor-0.0.56.dist-info/WHEEL
bruhcolor-0.0.56.dist-info/top_level.txt
bruhcolor-0.0.56.dist-info/RECORD
