Metadata-Version: 2.1
Name: bruhcolor
Version: 0.0.56
Summary: 256 Color Terminal Text Formatter
Author: Ethan Christensen
Author-email: ethanlchristensen@outlook.com
Keywords: python,terminal,text coloring,bruhcolor
Classifier: Development Status :: 4 - Beta
Classifier: Intended Audience :: Developers
Classifier: Programming Language :: Python :: 3
Classifier: Operating System :: Unix
Classifier: Operating System :: MacOS :: MacOS X
Classifier: Operating System :: Microsoft :: Windows
License-File: COPYING.txt
